{
    "apk_info": {
        "id": "Lj2Vd05XyjR18ykY",
        "url": "https://developer.koodous.com/apks/dbb1e7fb7ea95efe708ecae85bc6ceb9fe89adfd80a03202b21d052a05750283/",
        "sha256": "dbb1e7fb7ea95efe708ecae85bc6ceb9fe89adfd80a03202b21d052a05750283",
        "md5": "699780c4ccd058ff71835f88cf0ed9a0",
        "sha1": "9c07ce4cc0050e3f6c9e4fabe3c58ba2118cefe3",
        "app": "Mia Khalifa",
        "package_name": "com.appolonis.MiaKhalifa",
        "company": "bilal kamoon",
        "version": "1.0",
        "image": "https://developer.koodous.com/media/apk_images/11/cf/11cf7be3879cf4cebc6396ba7bac96d8117a28bfe45b159a6aedae9187a594c5",
        "size": 1254120,
        "tags": [
            "smssend",
            "checks-gps",
            "spyware",
            "trojan",
            "telephony",
            "maikspy",
            "flep",
            "andr"
        ],
        "is_trusted": false,
        "is_installed": false,
        "rating": -3,
        "is_detected": true,
        "is_corrupted": false,
        "last_scan": null,
        "is_static_analyzed": true,
        "is_dynamic_analyzed": true,
        "is_false_positive": false,
        "last_yara_analysis_at": null,
        "matches_count": 0,
        "comments_count": 0,
        "votes_count": 3,
        "created_at": "2018-05-09T03:19:02+02:00",
        "updated_at": "2025-05-30T16:18:32.853976+02:00"
    },
    "static_analysis": {
        "cuckoo": {
            "file": {
                "md5": "699780c4ccd058ff71835f88cf0ed9a0",
                "name": "",
                "path": "",
                "sha1": "9c07ce4cc0050e3f6c9e4fabe3c58ba2118cefe3",
                "size": 1254120,
                "type": "Android package (APK), with AndroidManifest.xml",
                "yara": [],
                "crc32": "80A6D1B",
                "sha256": "dbb1e7fb7ea95efe708ecae85bc6ceb9fe89adfd80a03202b21d052a05750283",
                "sha512": "bb50da878df5d7214bd21a6a6e55dfb9b890c4564dd16c64706f52ca367337604b493964789596f7bf2fba1f15dd9088b8e8eea745883f596d9b7d546917a670",
                "ssdeep": "24576:KSJmhQ974ejVB777777777777Jyq2qHmJmhQ974ejVB777777777777Jyq2qfOaH:JJmhQ974YVB777777777777H2qHmJmhY"
            },
            "file_id": "",
            "category": "file"
        },
        "androguard": {
            "urls": [
                "http://schemas.android.com/apk/res/android",
                "http://roundyearfun.org/ping.php?name=",
                "http://www.opengis.net/kml/2.2",
                "http://roundyearfun.org/notify.php?type=android&name="
            ],
            "dexes": {
                "classes": {
                    "sha256": "bf10c77426c578e86ccf660262f1ba74647dfa41212fba1e8fc2550a1b769d2b"
                }
            },
            "api_key": {},
            "cordova": "",
            "filters": [
                "android.intent.action.NEW_OUTGOING_CALL",
                "android.intent.action.MAIN",
                "android.intent.action.PHONE_STATE",
                "android.intent.action.BOOT_COMPLETED"
            ],
            "app_name": "Mia Khalifa",
            "services": [
                "com.appolonis.MiaKhalifa.service",
                "com.appolonis.MiaKhalifa.Record"
            ],
            "wearable": false,
            "androidtv": false,
            "libraries": [],
            "providers": [],
            "receivers": [
                "com.appolonis.MiaKhalifa.Alarm",
                "com.appolonis.MiaKhalifa.AutoStart",
                "com.appolonis.MiaKhalifa.Record.PhonecallReceiver",
                "com.appolonis.MiaKhalifa.CallReciever"
            ],
            "activities": [
                "com.appolonis.MiaKhalifa.Firsttime"
            ],
            "certificate": {
                "sha1": "0FAF0D257200C3DDD16FBADD4201110EFA4FEA0E",
                "serial": "35140E84",
                "sha256": "27FABC5728B63B36305DBB2F95A591A6224AF6D7E1C5849D6818D633D99FCFF9",
                "issuerDN": "CN = bilal kamoon",
                "not_after": "Feb 01 12:26:48 2049 GMT",
                "subjectDN": "CN = bilal kamoon",
                "not_before": "Feb 10 12:26:48 2016 GMT",
                "hash_algorithm": "sha256",
                "signature_algorithm": "rsassa_pkcs1v15"
            },
            "permissions": [
                "android.permission.READ_PHONE_STATE",
                "android.permission.RECEIVE_SMS",
                "android.permission.READ_SMS",
                "android.permission.INTERNET",
                "android.permission.CAMERA",
                "android.permission.WAKE_LOCK",
                "android.permission.WRITE_EXTERNAL_STORAGE",
                "android.permission.ACCESS_NETWORK_STATE",
                "android.permission.PROCESS_OUTGOING_CALLS",
                "android.permission.STORAGE",
                "android.permission.ACCESS_FINE_LOCATION",
                "android.permission.SEND_SMS",
                "android.permission.READ_CONTACTS",
                "android.permission.GET_ACCOUNTS",
                "android.permission.BLUETOOTH",
                "android.permission.ACCESS_COARSE_LOCATION",
                "android.permission.RECORD_AUDIO",
                "android.permission.RECEIVE_BOOT_COMPLETED",
                "android.permission.READ_EXTERNAL_STORAGE",
                "android.permission.WRITE_SMS"
            ],
            "is_signed_v1": true,
            "is_signed_v2": false,
            "is_signed_v3": false,
            "package_name": "com.appolonis.MiaKhalifa",
            "version_code": "1",
            "main_activity": "com.appolonis.MiaKhalifa.Firsttime",
            "signature_name": "META-INF/CERT.RSA",
            "files_by_format": {
                "bin": 8,
                "jpg": 2,
                "png": 5,
                "txt": 2
            },
            "functionalities": {
                "SMS": [
                    {
                        "code": "invoke-virtual/range v13 ... v18, Landroid/telephony/SmsManager;->sendTextMessage(Ljava/lang/String; Ljava/lang/String; Ljava/lang/String; Landroid/app/PendingIntent; Landroid/app/PendingIntent;)V",
                        "class": "Lcom/appolonis/MiaKhalifa/Alarm;",
                        "method": "onReceive"
                    }
                ],
                "crypto": [
                    {
                        "code": "invoke-virtual v5, v8, Ljava/security/MessageDigest;->digest([B)[B",
                        "class": "Lorg/apache/commons/net/pop3/POP3Client;",
                        "method": "login"
                    }
                ],
                "socket": [
                    {
                        "code": "invoke-interface v1, v2, Landroid/support/v4/app/NotificationManagerCompat$Task;->send(Landroid/support/v4/app/INotificationSideChannel;)V",
                        "class": "Landroid/support/v4/app/NotificationManagerCompat$SideChannelManager;",
                        "method": "processListenerQueue"
                    },
                    {
                        "code": "invoke-virtual v1, v0, Landroid/os/Messenger;->send(Landroid/os/Message;)V",
                        "class": "Landroid/support/v4/media/MediaBrowserCompat$ServiceBinderWrapper;",
                        "method": "sendRequest"
                    },
                    {
                        "code": "invoke-interface v0, v3, v4, Landroid/support/v4/os/IResultReceiver;->send(I Landroid/os/Bundle;)V",
                        "class": "Landroid/support/v4/os/ResultReceiver;",
                        "method": "send"
                    }
                ],
                "accounts": [
                    {
                        "code": "invoke-virtual/range v22, Landroid/accounts/AccountManager;->getAccounts()[Landroid/accounts/Account;",
                        "class": "Lcom/appolonis/MiaKhalifa/Alarm;",
                        "method": "onReceive"
                    }
                ],
                "runbinary": [
                    {
                        "code": "invoke-virtual v1, v2, v3, v4, v0, Lorg/apache/commons/net/bsd/RExecClient;->rexec(Ljava/lang/String; Ljava/lang/String; Ljava/lang/String; Z)V",
                        "class": "Lorg/apache/commons/net/bsd/RExecClient;",
                        "method": "rexec"
                    },
                    {
                        "code": "invoke-virtual v0, v1, v2, v3, v4, Lorg/apache/commons/net/bsd/RCommandClient;->rexec(Ljava/lang/String; Ljava/lang/String; Ljava/lang/String; Z)V",
                        "class": "Lorg/apache/commons/net/bsd/RCommandClient;",
                        "method": "rcommand"
                    },
                    {
                        "code": "invoke-virtual v1, v2, v3, v4, v0, Lorg/apache/commons/net/bsd/RLoginClient;->rexec(Ljava/lang/String; Ljava/lang/String; Ljava/lang/String; Z)V",
                        "class": "Lorg/apache/commons/net/bsd/RLoginClient;",
                        "method": "rlogin"
                    }
                ],
                "phonenumber": [
                    {
                        "code": "invoke-virtual/range v88, Landroid/telephony/TelephonyManager;->getLine1Number()Ljava/lang/String;",
                        "class": "Lcom/appolonis/MiaKhalifa/Alarm;",
                        "method": "onReceive"
                    },
                    {
                        "code": "invoke-virtual/range v88, Landroid/telephony/TelephonyManager;->getLine1Number()Ljava/lang/String;",
                        "class": "Lcom/appolonis/MiaKhalifa/Alarm;",
                        "method": "onReceive"
                    }
                ],
                "dynamicbroadcastreceiver": [
                    {
                        "code": "invoke-virtual v0, v1, v2, Landroid/content/Context;->registerReceiver(Landroid/content/BroadcastReceiver; Landroid/content/IntentFilter;)Landroid/content/Intent;",
                        "class": "Landroid/support/v4/media/TransportMediatorJellybeanMR2;",
                        "method": "windowAttached"
                    },
                    {
                        "code": "invoke-virtual v0, v1, Landroid/content/Context;->unregisterReceiver(Landroid/content/BroadcastReceiver;)V",
                        "class": "Landroid/support/v4/media/TransportMediatorJellybeanMR2;",
                        "method": "windowDetached"
                    },
                    {
                        "code": "invoke-virtual v2, v1, v0, Lcom/appolonis/MiaKhalifa/Record;->registerReceiver(Landroid/content/BroadcastReceiver; Landroid/content/IntentFilter;)Landroid/content/Intent;",
                        "class": "Lcom/appolonis/MiaKhalifa/Record;",
                        "method": "onCreate"
                    }
                ]
            },
            "max_sdk_version": "",
            "min_sdk_version": 15,
            "new_permissions": [],
            "displayed_version": "1.0",
            "androguard_version": "4.1.1",
            "files_by_extension": {
                "MF": 1,
                "SF": 1,
                "RSA": 1,
                "dex": 1,
                "jpg": 2,
                "png": 5,
                "xml": 5,
                "arsc": 1
            },
            "target_sdk_version": 25
        }
    },
    "dynamic_analysis": {
        "droidbox": {
            "dns": [],
            "debug": [],
            "phone": [],
            "recvnet": [],
            "sendnet": [],
            "sendsms": [],
            "dexclass": [],
            "filesopen": [
                {
                    "pid": 4278,
                    "tid": 4278,
                    "name": "/proc/self/cmdline",
                    "time": 1.0643589496612549,
                    "processname": "com.appolonis.MiaKhalifa"
                },
                {
                    "pid": 4278,
                    "tid": 4278,
                    "name": "/system/framework/org.apache.http.legacy.boot.jar.x86_64.flock",
                    "time": 1.0800230503082275,
                    "processname": "com.appolonis.MiaKhalifa"
                },
                {
                    "pid": 4278,
                    "tid": 4278,
                    "name": "/system/framework/oat/x86_64/org.apache.http.legacy.boot.vdex",
                    "time": 1.0800859928131104,
                    "processname": "com.appolonis.MiaKhalifa"
                },
                {
                    "pid": 4278,
                    "tid": 4278,
                    "name": "/data/dalvik-cache/x86_64/system@framework@boot.art",
                    "time": 1.0812790393829346,
                    "processname": "com.appolonis.MiaKhalifa"
                },
                {
                    "pid": 4278,
                    "tid": 4278,
                    "name": "/data/dalvik-cache/x86_64/system@framework@boot-core-libart.art",
                    "time": 1.0813820362091064,
                    "processname": "com.appolonis.MiaKhalifa"
                },
                {
                    "pid": 4278,
                    "tid": 4278,
                    "name": "/data/dalvik-cache/x86_64/system@framework@boot-conscrypt.art",
                    "time": 1.0814290046691895,
                    "processname": "com.appolonis.MiaKhalifa"
                },
                {
                    "pid": 4278,
                    "tid": 4278,
                    "name": "/data/dalvik-cache/x86_64/system@framework@boot-okhttp.art",
                    "time": 1.0815348625183105,
                    "processname": "com.appolonis.MiaKhalifa"
                },
                {
                    "pid": 4278,
                    "tid": 4278,
                    "name": "/data/dalvik-cache/x86_64/system@framework@boot-bouncycastle.art",
                    "time": 1.0816638469696045,
                    "processname": "com.appolonis.MiaKhalifa"
                },
                {
                    "pid": 4278,
                    "tid": 4278,
                    "name": "/data/dalvik-cache/x86_64/system@framework@boot-apache-xml.art",
                    "time": 1.0843398571014404,
                    "processname": "com.appolonis.MiaKhalifa"
                },
                {
                    "pid": 4278,
                    "tid": 4278,
                    "name": "/data/dalvik-cache/x86_64/system@framework@boot-ext.art",
                    "time": 1.0844089984893799,
                    "processname": "com.appolonis.MiaKhalifa"
                },
                {
                    "pid": 4278,
                    "tid": 4278,
                    "name": "/data/dalvik-cache/x86_64/system@framework@boot-framework.art",
                    "time": 1.084502935409546,
                    "processname": "com.appolonis.MiaKhalifa"
                },
                {
                    "pid": 4278,
                    "tid": 4278,
                    "name": "/data/dalvik-cache/x86_64/system@framework@boot-telephony-common.art",
                    "time": 1.084580898284912,
                    "processname": "com.appolonis.MiaKhalifa"
                },
                {
                    "pid": 4278,
                    "tid": 4278,
                    "name": "/data/dalvik-cache/x86_64/system@framework@boot-voip-common.art",
                    "time": 1.0846688747406006,
                    "processname": "com.appolonis.MiaKhalifa"
                },
                {
                    "pid": 4278,
                    "tid": 4278,
                    "name": "/data/dalvik-cache/x86_64/system@framework@boot-ims-common.art",
                    "time": 1.0847480297088623,
                    "processname": "com.appolonis.MiaKhalifa"
                },
                {
                    "pid": 4278,
                    "tid": 4278,
                    "name": "/data/dalvik-cache/x86_64/system@framework@boot-android.hidl.manager-V1.0-java.art",
                    "time": 1.084826946258545,
                    "processname": "com.appolonis.MiaKhalifa"
                },
                {
                    "pid": 4278,
                    "tid": 4278,
                    "name": "/data/dalvik-cache/x86_64/system@framework@boot-framework-oahl-backward-compatibility.art",
                    "time": 1.084925889968872,
                    "processname": "com.appolonis.MiaKhalifa"
                },
                {
                    "pid": 4278,
                    "tid": 4278,
                    "name": "/data/dalvik-cache/x86_64/system@framework@boot-android.test.base.art",
                    "time": 1.08502197265625,
                    "processname": "com.appolonis.MiaKhalifa"
                },
                {
                    "pid": 4278,
                    "tid": 4278,
                    "name": "/system/framework/org.apache.http.legacy.boot.jar",
                    "time": 1.0851218700408936,
                    "processname": "com.appolonis.MiaKhalifa"
                },
                {
                    "pid": 4278,
                    "tid": 4278,
                    "name": "/system/framework/x86_64/boot.art",
                    "time": 1.0853638648986816,
                    "processname": "com.appolonis.MiaKhalifa"
                },
                {
                    "pid": 4278,
                    "tid": 4278,
                    "name": "/data/dalvik-cache/x86_64/system@framework@boot.art",
                    "time": 1.0855739116668701,
                    "processname": "com.appolonis.MiaKhalifa"
                },
                {
                    "pid": 4278,
                    "tid": 4278,
                    "name": "/system/framework/oat/x86_64/org.apache.http.legacy.boot.art",
                    "time": 1.0857648849487305,
                    "processname": "com.appolonis.MiaKhalifa"
                },
                {
                    "pid": 4278,
                    "tid": 4278,
                    "name": "/data/app/com.appolonis.MiaKhalifa-Vy7esoehNGSbCRRIuc3oSQ==/base.apk.x86_64.flock",
                    "time": 1.0858478546142578,
                    "processname": "com.appolonis.MiaKhalifa"
                },
                {
                    "pid": 4278,
                    "tid": 4278,
                    "name": "/data/app/com.appolonis.MiaKhalifa-Vy7esoehNGSbCRRIuc3oSQ==/oat/x86_64/base.vdex",
                    "time": 1.0860519409179688,
                    "processname": "com.appolonis.MiaKhalifa"
                },
                {
                    "pid": 4278,
                    "tid": 4278,
                    "name": "/data/app/com.appolonis.MiaKhalifa-Vy7esoehNGSbCRRIuc3oSQ==/base.apk",
                    "time": 1.0861539840698242,
                    "processname": "com.appolonis.MiaKhalifa"
                },
                {
                    "pid": 4278,
                    "tid": 4278,
                    "name": "/system/framework/x86_64/boot.art",
                    "time": 1.0863628387451172,
                    "processname": "com.appolonis.MiaKhalifa"
                },
                {
                    "pid": 4278,
                    "tid": 4278,
                    "name": "/data/dalvik-cache/x86_64/system@framework@boot.art",
                    "time": 1.086555004119873,
                    "processname": "com.appolonis.MiaKhalifa"
                },
                {
                    "pid": 4278,
                    "tid": 4278,
                    "name": "/data/app/com.appolonis.MiaKhalifa-Vy7esoehNGSbCRRIuc3oSQ==/oat/x86_64/base.art",
                    "time": 1.0867459774017334,
                    "processname": "com.appolonis.MiaKhalifa"
                },
                {
                    "pid": 4278,
                    "tid": 4278,
                    "name": "/data/app/com.appolonis.MiaKhalifa-Vy7esoehNGSbCRRIuc3oSQ==/base.apk",
                    "time": 1.0981059074401855,
                    "processname": "com.appolonis.MiaKhalifa"
                },
                {
                    "pid": 4278,
                    "tid": 4386,
                    "name": "/data/user_de/0/com.appolonis.MiaKhalifa/code_cache/com.android.skia.shaders_cache",
                    "time": 1.6432240009307861,
                    "processname": "com.appolonis.MiaKhalifa"
                }
            ],
            "filesread": [
                {
                    "pid": 4278,
                    "tid": 4278,
                    "data": "636f6d2e6170706f6c6f6e69732e4d69614b68616c696661000000000000000000000000000000000000000000000000000000000000000000000000000000000000000000000000000000000000000000000000000000000000000000000000000000",
                    "name": "/proc/self/cmdline",
                    "time": 1.0799310207366943,
                    "processname": "com.appolonis.MiaKhalifa"
                },
                {
                    "pid": 4278,
                    "tid": 4278,
                    "data": "",
                    "name": "/proc/self/cmdline",
                    "time": 1.0799829959869385,
                    "processname": "com.appolonis.MiaKhalifa"
                },
                {
                    "pid": 4278,
                    "tid": 4278,
                    "data": "504b0304",
                    "name": "/system/framework/org.apache.http.legacy.boot.jar",
                    "time": 1.0852389335632324,
                    "processname": "com.appolonis.MiaKhalifa"
                },
                {
                    "pid": 4278,
                    "tid": 4278,
                    "data": "6172740a303536000000007044e42e00aef4696f00f02371000024716f306d710050b57100000000000000000000000000000000000000006077007008000000010000000000000000000000a8cb1500a8cb1500e006020088d21700c0b40e0008bb2b00c8f0000048872600e0f70300287f2a00e03b0100d0ab2c0000e0000000902d006800010068902e00dc53000000f02e000060000008bb2b700000000030bb2b700000000058bb2b700000000080bb2b7000000000a8bb2b7000000000d0bb2b7000000000f8bb2b700000000020bc2b700000000048bc2b7000000000000000005ce32e00",
                    "name": "/system/framework/x86_64/boot.art",
                    "time": 1.085460901260376,
                    "processname": "com.appolonis.MiaKhalifa"
                },
                {
                    "pid": 4278,
                    "tid": 4278,
                    "data": "6172740a3035360000e0696f44e42e00aef4696f00d08d7000e08d706f10d77000301f710000000000000000000000000000000000e069ff60576a6f08000000010000000000000000000000a8cb1500a8cb1500e006020088d21700c0b40e0008bb2b00c8f0000048872600e0f70300287f2a00e03b0100d0ab2c0000e0000000902d006800010068902e00dc53000000f02e0000600000089b956f00000000309b956f00000000589b956f00000000809b956f00000000a89b956f00000000d09b956f00000000f89b956f00000000209c956f00000000489c956f00000000000000005ce32e00",
                    "name": "/data/dalvik-cache/x86_64/system@framework@boot.art",
                    "time": 1.0856540203094482,
                    "processname": "com.appolonis.MiaKhalifa"
                },
                {
                    "pid": 4278,
                    "tid": 4278,
                    "data": "504b0304",
                    "name": "/data/app/com.appolonis.MiaKhalifa-Vy7esoehNGSbCRRIuc3oSQ==/base.apk",
                    "time": 1.0862460136413574,
                    "processname": "com.appolonis.MiaKhalifa"
                },
                {
                    "pid": 4278,
                    "tid": 4278,
                    "data": "6172740a303536000000007044e42e00aef4696f00f02371000024716f306d710050b57100000000000000000000000000000000000000006077007008000000010000000000000000000000a8cb1500a8cb1500e006020088d21700c0b40e0008bb2b00c8f0000048872600e0f70300287f2a00e03b0100d0ab2c0000e0000000902d006800010068902e00dc53000000f02e000060000008bb2b700000000030bb2b700000000058bb2b700000000080bb2b7000000000a8bb2b7000000000d0bb2b7000000000f8bb2b700000000020bc2b700000000048bc2b7000000000000000005ce32e00",
                    "name": "/system/framework/x86_64/boot.art",
                    "time": 1.0864629745483398,
                    "processname": "com.appolonis.MiaKhalifa"
                },
                {
                    "pid": 4278,
                    "tid": 4278,
                    "data": "6172740a3035360000e0696f44e42e00aef4696f00d08d7000e08d706f10d77000301f710000000000000000000000000000000000e069ff60576a6f08000000010000000000000000000000a8cb1500a8cb1500e006020088d21700c0b40e0008bb2b00c8f0000048872600e0f70300287f2a00e03b0100d0ab2c0000e0000000902d006800010068902e00dc53000000f02e0000600000089b956f00000000309b956f00000000589b956f00000000809b956f00000000a89b956f00000000d09b956f00000000f89b956f00000000209c956f00000000489c956f00000000000000005ce32e00",
                    "name": "/data/dalvik-cache/x86_64/system@framework@boot.art",
                    "time": 1.0866539478302002,
                    "processname": "com.appolonis.MiaKhalifa"
                },
                {
                    "pid": 4278,
                    "tid": 4278,
                    "data": "6172740a3035360000803d78200401002cf921bf00903e7800a03e7800203f7800405d7800e0696f90ef230100e08d7022f1ae030000000050813d780800000000000000010000000000000088040000880400000000000088040000000000008804000000000000880400000000000088040000000000009004000000e0000090e40000c80f000058f40000c80f00000010010000100000089b956f00000000309b956f00000000589b956f00000000809b956f00000000a89b956f00000000d09b956f00000000f89b956f00000000209c956f00000000489c956f0000000001000000965e0000",
                    "name": "/data/app/com.appolonis.MiaKhalifa-Vy7esoehNGSbCRRIuc3oSQ==/oat/x86_64/base.art",
                    "time": 1.086845874786377,
                    "processname": "com.appolonis.MiaKhalifa"
                }
            ],
            "libraries": [],
            "processes": [],
            "phonecalls": [],
            "cryptousage": [],
            "fingerprint": [],
            "filesdeleted": [
                {
                    "pid": 4278,
                    "tid": 4278,
                    "name": "/system/framework/org.apache.http.legacy.boot.jar.x86_64.flock",
                    "time": 1.0800540447235107,
                    "processname": "com.appolonis.MiaKhalifa"
                },
                {
                    "pid": 4278,
                    "tid": 4278,
                    "name": "/data/app/com.appolonis.MiaKhalifa-Vy7esoehNGSbCRRIuc3oSQ==/base.apk.x86_64.flock",
                    "time": 1.0859508514404297,
                    "processname": "com.appolonis.MiaKhalifa"
                }
            ],
            "fileswritten": [],
            "servicestart": []
        }
    }
}